{
  "Rows": {
    "RowColumnAttachedInfos": {
      "0": {
        "GridRowColumnDefinition": {
          "DesignLengthInPixel": 12.0
        }
      },
      "1": {
        "GridRowColumnDefinition": {
          "DesignLengthInPixel": 20.0
        }
      },
      "2": {
        "GridRowColumnDefinition": {
          "DesignLengthInPixel": 20.0
        }
      },
      "3": {
        "GridRowColumnDefinition": {
          "DesignLengthInPixel": 12.0
        }
      },
      "4": {
        "GridRowColumnDefinition": {
          "DesignLengthInPixel": 20.0
        }
      },
      "5": {
        "GridRowColumnDefinition": {
          "DesignLengthInPixel": 20.0
        }
      },
      "6": {
        "GridRowColumnDefinition": {
          "DesignLengthInPixel": 20.0
        }
      },
      "7": {
        "GridRowColumnDefinition": {
          "DesignLengthInPixel": 20.0
        }
      },
      "8": {
        "GridRowColumnDefinition": {
          "DesignLengthInPixel": 10.0
        }
      },
      "9": {
        "GridRowColumnDefinition": {
          "DesignLengthInPixel": 20.0
        }
      },
      "10": {
        "GridRowColumnDefinition": {
          "DesignLengthInPixel": 20.0
        }
      },
      "11": {
        "GridRowColumnDefinition": {
          "DesignLengthInPixel": 20.0
        }
      },
      "12": {
        "GridRowColumnDefinition": {
          "DesignLengthInPixel": 20.0
        }
      },
      "13": {
        "GridRowColumnDefinition": {
          "DesignLengthInPixel": 20.0
        }
      },
      "14": {
        "GridRowColumnDefinition": {
          "DesignLengthInPixel": 20.0
        }
      },
      "15": {
        "GridRowColumnDefinition": {
          "DesignLengthInPixel": 20.0
        }
      },
      "20": {
        "GridRowColumnDefinition": {
          "DesignLengthInPixel": 20.0
        }
      },
      "21": {
        "GridRowColumnDefinition": {
          "DesignLengthInPixel": 20.0
        }
      },
      "22": {
        "GridRowColumnDefinition": {
          "DesignLengthInPixel": 20.0
        }
      },
      "23": {
        "GridRowColumnDefinition": {
          "DesignLengthInPixel": 20.0
        }
      },
      "24": {
        "GridRowColumnDefinition": {
          "DesignLengthInPixel": 20.0
        }
      },
      "25": {
        "GridRowColumnDefinition": {
          "DesignLengthInPixel": 20.0
        }
      },
      "41": {
        "GridRowColumnDefinition": {
          "DesignLengthInPixel": 10.0
        }
      }
    },
    "Count": 42
  },
  "Cols": {
    "RowColumnAttachedInfos": {
      "0": {
        "GridRowColumnDefinition": {
          "DesignLengthInPixel": 10.0
        }
      },
      "1": {
        "GridRowColumnDefinition": {
          "DesignLengthInPixel": 24.0
        }
      },
      "2": {
        "GridRowColumnDefinition": {
          "DesignLengthInPixel": 20.0
        }
      },
      "6": {
        "GridRowColumnDefinition": {
          "DesignLengthInPixel": 20.0
        }
      },
      "26": {
        "GridRowColumnDefinition": {
          "DesignLengthInPixel": 20.0
        }
      },
      "30": {
        "GridRowColumnDefinition": {
          "DesignLengthInPixel": 20.0
        }
      },
      "31": {
        "GridRowColumnDefinition": {
          "DesignLengthInPixel": 20.0
        }
      },
      "32": {
        "GridRowColumnDefinition": {
          "DesignLengthInPixel": 20.0
        }
      },
      "33": {
        "GridRowColumnDefinition": {
          "DesignLengthInPixel": 20.0
        }
      },
      "34": {
        "GridRowColumnDefinition": {
          "DesignLengthInPixel": 20.0
        }
      },
      "35": {
        "GridRowColumnDefinition": {
          "DesignLengthInPixel": 20.0
        }
      },
      "36": {
        "GridRowColumnDefinition": {
          "DesignLengthInPixel": 20.0
        }
      },
      "37": {
        "GridRowColumnDefinition": {
          "DesignLengthInPixel": 20.0
        }
      },
      "38": {
        "GridRowColumnDefinition": {
          "DesignLengthInPixel": 20.0
        }
      },
      "39": {
        "GridRowColumnDefinition": {
          "DesignLengthInPixel": 10.0
        }
      }
    },
    "InLogicalVisibleIndexes": [
      40
    ],
    "Count": 41
  },
  "Values": {
    "4,29": "更新日時",
    "5,29": "更新者",
    "6,29": "作成日時",
    "7,29": "作成者",
    "9,1": "*",
    "9,2": "登録日",
    "9,25": "ID",
    "10,1": "*",
    "10,2": "件  名",
    "11,1": "作業者",
    "12,1": "メ　　　モ",
    "16,1": "校正証明書\n一覧",
    "20,1": "添付ファイル"
  },
  "AttachInfos": {
    "1,2": {
      "CellType": {
        "$type": "Forguncy.ButtonCellType, ServerDesignerCommon",
        "CommandList": [
          {
            "$type": "Forguncy.Model.ConditionCommand, ServerDesignerCommon",
            "ConditionAndCommandPairList": [
              {
                "ConfirmDialogSettings": {
                  "Title": "確認",
                  "FormulaText": "本当に実行してもよろしいですか？",
                  "YesButtonText": "はい",
                  "NoButtonText": "いいえ",
                  "ConfirmIcon": 1
                },
                "CommandList": [
                  {
                    "$type": "Forguncy.Model.UpdateDataTableCommand, ServerDesignerCommon",
                    "TableName": "trn_insptool_certifications",
                    "ShowConfirm": false,
                    "ConfirmText": "本当に更新してもよろしいですか？",
                    "UpdateValues": [],
                    "ParamNameToSaveNewRowValue": "NewRow"
                  }
                ],
                "ID": "e4cc0265-fc2d-4c55-8f41-845c8089d5fe"
              }
            ]
          }
        ],
        "AutoExecute": true,
        "TemplateKey": "_RS_Normal_Style2",
        "Icon": {
          "Name": "Application/069_save_6.svg",
          "BuiltIn": true,
          "Color": "Background 1",
          "UseCellTypeForeColor": true
        },
        "IconSize": 30.0
      }
    },
    "1,40": {
      "CellType": {
        "$type": "Forguncy.TextCellType, ServerDesignerCommon",
        "SavedValidators": [
          {
            "$type": "Forguncy.CellTypes.Models.UniqueValidadator, ServerDesignerCommon",
            "Enabled": true
          }
        ],
        "TemplateKey": "_RS_LightLine_Translucent_SmallRoundCorner_Normal1"
      },
      "BindingInfo": {
        "TableName": "trn_insptool_certifications",
        "ColumnName": "id"
      },
      "DataValidationInfo": {
        "IgnoreBlank": false
      }
    },
    "4,1": {
      "ListViewInfo": {
        "ShowColumnHeaderInDesigner": true,
        "TableName": "trn_insptool_tools",
        "RowIndex": 4,
        "ColumnIndex": 1,
        "ColumnCount": 4,
        "RowCount": 4,
        "ColumnOperation": 2,
        "ShowEditStatusIcon": true,
        "UseSimpleBar": true,
        "Name": "リストビュー1",
        "TopCondition": null,
        "ListViewStyleName": "_RS_ListStyle1"
      }
    },
    "4,30": {
      "BindingInfo": {
        "TableName": "trn_insptool_certifications",
        "ColumnName": "FGC_LastModifyDate"
      }
    },
    "5,1": {
      "BindingInfo": {
        "TableName": "trn_insptool_tools",
        "ColumnName": "ctrl_no"
      }
    },
    "5,30": {
      "BindingInfo": {
        "TableName": "trn_insptool_certifications",
        "ColumnName": "FGC_LastModifier",
        "AttachType": {
          "$type": "ForguncyDataAccess.UserColumnAttachObj, ForguncyDataAccess",
          "UserColumnAttachType": 1
        }
      }
    },
    "6,30": {
      "BindingInfo": {
        "TableName": "trn_insptool_certifications",
        "ColumnName": "FGC_CreateDate"
      }
    },
    "7,30": {
      "BindingInfo": {
        "TableName": "trn_insptool_certifications",
        "ColumnName": "FGC_Creator",
        "AttachType": {
          "$type": "ForguncyDataAccess.UserColumnAttachObj, ForguncyDataAccess",
          "UserColumnAttachType": 1
        }
      }
    },
    "9,6": {
      "BindingInfo": {
        "TableName": "trn_insptool_certifications",
        "ColumnName": "registration_date"
      }
    },
    "9,30": {
      "BindingInfo": {
        "TableName": "trn_insptool_certifications",
        "ColumnName": "id"
      }
    },
    "10,6": {
      "CellType": {
        "$type": "Forguncy.TextCellType, ServerDesignerCommon",
        "SavedValidators": [
          {
            "$type": "Forguncy.CellTypes.Models.UniqueValidadator, ServerDesignerCommon"
          }
        ],
        "TemplateKey": "_RS_LightLine_Translucent_SmallRoundCorner_Normal1"
      },
      "BindingInfo": {
        "TableName": "trn_insptool_certifications",
        "ColumnName": "subject"
      },
      "DataValidationInfo": {
        "IgnoreBlank": false
      }
    },
    "11,6": {
      "CellType": {
        "$type": "Forguncy.TextCellType, ServerDesignerCommon",
        "SavedValidators": [
          {
            "$type": "Forguncy.CellTypes.Models.UniqueValidadator, ServerDesignerCommon"
          }
        ],
        "TemplateKey": "_RS_LightLine_Translucent_SmallRoundCorner_Normal1"
      },
      "BindingInfo": {
        "TableName": "trn_insptool_certifications",
        "ColumnName": "calibrator"
      }
    },
    "12,6": {
      "CellType": {
        "$type": "Forguncy.MultilineTextBox, ServerDesignerCommon",
        "TemplateKey": "_RS_LightLine_Translucent_SmallRoundCorner_Normal1"
      },
      "BindingInfo": {
        "TableName": "trn_insptool_certifications",
        "ColumnName": "memo"
      }
    },
    "16,6": {
      "CellType": {
        "$type": "Forguncy.AttachmentCelltype, ServerDesignerCommon",
        "ReadOnly": true,
        "TemplateKey": "_RS_Normal_Style2"
      },
      "BindingInfo": {
        "TableName": "trn_insptool_certifications",
        "ColumnName": "attachment_list"
      }
    },
    "19,1": {
      "CellType": {
        "$type": "Forguncy.CheckBoxCellType, ServerDesignerCommon",
        "Caption": "編集可",
        "Style": 1,
        "CommandList": [
          {
            "$type": "Forguncy.Model.ConditionCommand, ServerDesignerCommon",
            "ConditionAndCommandPairList": [
              {
                "Condition": {
                  "$type": "Forguncy.Model.IfCondition, ServerDesignerCommon",
                  "param": {
                    "$type": "Forguncy.Model.IfConditionPageElementParam, ServerDesignerCommon",
                    "cellLocations": [
                      {
                        "SerializeProperty": "=記録文書の編集!B20"
                      }
                    ]
                  },
                  "value": "True"
                },
                "CommandList": [
                  {
                    "$type": "Forguncy.Model.SetCellPropertyCommand, ServerDesignerCommon",
                    "PropertyItemsList": [
                      {
                        "TargetCells": {
                          "$type": "Forguncy.Model.FormulaReferObject, ServerDesignerCommon",
                          "SerializeProperty": "=記録文書の編集!G17"
                        },
                        "PropertyType": 5,
                        "Value": false
                      }
                    ]
                  }
                ],
                "ID": "ac2fe0c3-e221-40a7-9a6b-f6eb04df82b4"
              },
              {
                "CommandList": [
                  {
                    "$type": "Forguncy.Model.SetCellPropertyCommand, ServerDesignerCommon",
                    "PropertyItemsList": [
                      {
                        "TargetCells": {
                          "$type": "Forguncy.Model.FormulaReferObject, ServerDesignerCommon",
                          "SerializeProperty": "=記録文書の編集!G17"
                        },
                        "PropertyType": 5,
                        "Value": true
                      }
                    ]
                  }
                ],
                "ID": "0eee9822-2767-4db4-8afb-a591ff2830e9"
              }
            ]
          }
        ]
      }
    },
    "20,6": {
      "CellType": {
        "$type": "Forguncy.AttachmentCelltype, ServerDesignerCommon",
        "ReadOnly": true,
        "TemplateKey": "_RS_Normal_Style2"
      },
      "BindingInfo": {
        "TableName": "trn_insptool_certifications",
        "ColumnName": "attachment"
      }
    },
    "22,1": {
      "CellType": {
        "$type": "Forguncy.CheckBoxCellType, ServerDesignerCommon",
        "Caption": "編集可",
        "Style": 1,
        "CommandList": [
          {
            "$type": "Forguncy.Model.ConditionCommand, ServerDesignerCommon",
            "ConditionAndCommandPairList": [
              {
                "Condition": {
                  "$type": "Forguncy.Model.IfCondition, ServerDesignerCommon",
                  "param": {
                    "$type": "Forguncy.Model.IfConditionPageElementParam, ServerDesignerCommon",
                    "cellLocations": [
                      {
                        "SerializeProperty": "=記録文書の編集!B23"
                      }
                    ]
                  },
                  "value": "True"
                },
                "CommandList": [
                  {
                    "$type": "Forguncy.Model.SetCellPropertyCommand, ServerDesignerCommon",
                    "PropertyItemsList": [
                      {
                        "TargetCells": {
                          "$type": "Forguncy.Model.FormulaReferObject, ServerDesignerCommon",
                          "SerializeProperty": "=記録文書の編集!G21"
                        },
                        "PropertyType": 5,
                        "Value": false
                      }
                    ]
                  }
                ],
                "ID": "0f0b5947-55b7-41a0-ac07-ea021cc4a2ba"
              },
              {
                "CommandList": [
                  {
                    "$type": "Forguncy.Model.SetCellPropertyCommand, ServerDesignerCommon",
                    "PropertyItemsList": [
                      {
                        "TargetCells": {
                          "$type": "Forguncy.Model.FormulaReferObject, ServerDesignerCommon",
                          "SerializeProperty": "=記録文書の編集!G21"
                        },
                        "PropertyType": 5,
                        "Value": true
                      }
                    ]
                  }
                ],
                "ID": "c9461b87-8bd7-489d-a87b-44649cb9e1e9"
              }
            ]
          }
        ]
      }
    }
  },
  "StyleDatas": {
    "Styles": [
      {
        "FontFamily": 0,
        "FontSize": 14.666666984558105,
        "BorderBottom": null,
        "BorderTop": null,
        "BorderLeft": null,
        "BorderRight": null
      },
      {
        "Background": 1,
        "FontFamily": 0,
        "FontSize": 14.666666984558105,
        "Foreground": 2,
        "Formatter": 3,
        "Underline": true,
        "BorderBottom": null,
        "BorderTop": null,
        "BorderLeft": null,
        "BorderRight": null
      },
      {
        "Background": 1,
        "FontFamily": 0,
        "FontSize": 14.666666984558105,
        "Formatter": 3,
        "BorderTop": null,
        "BorderLeft": null,
        "BorderRight": null
      },
      {
        "Background": 1,
        "FontFamily": 0,
        "FontSize": 14.666666984558105,
        "Formatter": 3,
        "BorderBottom": null,
        "BorderTop": null,
        "BorderLeft": null,
        "BorderRight": null
      },
      {
        "FontFamily": 0,
        "FontSize": 14.666666984558105,
        "Formatter": 4,
        "HorizontalAlignment": 5
      },
      {
        "FontFamily": 0,
        "FontSize": 14.666666984558105,
        "BorderBottom": 0,
        "BorderTop": null,
        "BorderLeft": null,
        "BorderRight": null
      },
      {
        "BorderBottom": 0
      },
      {
        "Foreground": 7
      },
      {
        "FontFamily": 0,
        "FontSize": 14.666666984558105,
        "FontWeight": 8,
        "Foreground": 9,
        "HorizontalAlignment": 5,
        "BorderBottom": null,
        "BorderTop": null,
        "BorderLeft": null,
        "BorderRight": null
      },
      {
        "FontFamily": 0,
        "FontSize": 14.666666984558105,
        "TextIndent": 5,
        "BorderBottom": 1
      },
      {
        "BorderBottom": 1
      },
      {
        "HorizontalAlignment": 5
      },
      {
        "Formatter": 4
      },
      {
        "FontFamily": null,
        "FontSize": -1.0,
        "BorderBottom": null,
        "BorderTop": null,
        "BorderLeft": null,
        "BorderRight": null
      },
      {
        "FontFamily": 0,
        "FontSize": 14.666666984558105,
        "FontWeight": 8,
        "Foreground": 9,
        "Formatter": 3,
        "HorizontalAlignment": 5,
        "BorderBottom": null,
        "BorderTop": null,
        "BorderLeft": null,
        "BorderRight": null
      },
      {
        "FontFamily": 0,
        "FontSize": 14.666666984558105,
        "TextIndent": 5
      },
      {
        "FontFamily": 0,
        "FontSize": 14.666666984558105
      },
      {
        "FontFamily": 0,
        "FontSize": 14.666666984558105,
        "TextIndent": 5,
        "BorderBottom": 1,
        "BorderTop": 1
      },
      {
        "BorderBottom": 1,
        "BorderTop": 1
      },
      {
        "FontFamily": null,
        "FontSize": -1.0,
        "BorderTop": null,
        "BorderLeft": null,
        "BorderRight": null
      },
      {
        "FontFamily": null,
        "FontSize": -1.0
      },
      {
        "Background": 10,
        "FontFamily": 0,
        "FontSize": 14.666666984558105,
        "Foreground": 11,
        "Formatter": 3,
        "HorizontalAlignment": 5,
        "VerticalAlignment": 12,
        "BorderBottom": 1,
        "BorderTop": 2,
        "BorderLeft": 2
      },
      {
        "Background": 10,
        "FontFamily": 0,
        "FontSize": 14.666666984558105,
        "FontWeight": 8,
        "Foreground": 9,
        "Formatter": 13,
        "HorizontalAlignment": 14,
        "VerticalAlignment": 12,
        "BorderBottom": 1,
        "BorderTop": 2,
        "BorderLeft": null
      },
      {
        "BorderBottom": 1,
        "BorderTop": 2
      },
      {
        "FontFamily": 0,
        "FontSize": 14.666666984558105,
        "Formatter": 15,
        "TextIndent": 5,
        "BorderBottom": 1,
        "BorderTop": 2,
        "BorderLeft": 1
      },
      {
        "Background": 10,
        "FontWeight": 8,
        "Foreground": 9,
        "HorizontalAlignment": 16,
        "BorderBottom": 1,
        "BorderTop": 2,
        "BorderLeft": 1
      },
      {
        "BorderBottom": 1,
        "BorderTop": 2,
        "BorderRight": 1
      },
      {
        "TextIndent": 5,
        "BorderBottom": 1,
        "BorderTop": 2
      },
      {
        "BorderBottom": 1,
        "BorderTop": 2,
        "BorderRight": 2
      },
      {
        "FontFamily": 0,
        "FontSize": 14.666666984558105,
        "Formatter": 15
      },
      {
        "Background": 10,
        "FontFamily": 0,
        "FontSize": 14.666666984558105,
        "Foreground": 11,
        "Formatter": 3,
        "HorizontalAlignment": 5,
        "VerticalAlignment": 12,
        "BorderBottom": 1,
        "BorderTop": 1,
        "BorderLeft": 2
      },
      {
        "Background": 10,
        "FontFamily": 0,
        "FontSize": 14.666666984558105,
        "FontWeight": 8,
        "Foreground": 9,
        "Formatter": 13,
        "HorizontalAlignment": 14,
        "VerticalAlignment": 12,
        "BorderBottom": 1,
        "BorderTop": 1,
        "BorderLeft": null
      },
      {
        "FontFamily": 0,
        "FontSize": 14.666666984558105,
        "Formatter": 4,
        "TextIndent": 5,
        "BorderBottom": 1,
        "BorderTop": 1,
        "BorderLeft": 1
      },
      {
        "BorderBottom": 1,
        "BorderTop": 1,
        "BorderRight": 2
      },
      {
        "Background": 10,
        "FontWeight": 8,
        "Foreground": 9,
        "Formatter": 13,
        "HorizontalAlignment": 16,
        "BorderLeft": 2
      },
      {
        "Formatter": 4,
        "BorderLeft": 1
      },
      {
        "BorderRight": 2
      },
      {
        "Background": 10,
        "FontFamily": 0,
        "FontSize": 14.666666984558105,
        "FontWeight": 8,
        "Foreground": 9,
        "Formatter": 13,
        "TextIndent": 20,
        "HorizontalAlignment": 14,
        "VerticalAlignment": 12,
        "BorderBottom": null,
        "BorderTop": 1,
        "BorderLeft": 2,
        "BorderRight": null
      },
      {
        "FontFamily": 0,
        "FontSize": 14.666666984558105,
        "BorderBottom": null,
        "BorderTop": 1,
        "BorderLeft": null,
        "BorderRight": null
      },
      {
        "FontFamily": 0,
        "FontSize": 14.666666984558105,
        "Formatter": 4,
        "VerticalAlignment": 12,
        "WordWrap": true,
        "BorderBottom": null,
        "BorderTop": 1,
        "BorderLeft": 1,
        "BorderRight": null
      },
      {
        "FontFamily": 0,
        "FontSize": 14.666666984558105,
        "BorderBottom": null,
        "BorderTop": 1,
        "BorderLeft": null,
        "BorderRight": 2
      },
      {
        "FontFamily": 0,
        "FontSize": 14.666666984558105,
        "BorderBottom": null,
        "BorderTop": null,
        "BorderLeft": 2,
        "BorderRight": null
      },
      {
        "FontFamily": 0,
        "FontSize": 14.666666984558105,
        "BorderBottom": null,
        "BorderTop": null,
        "BorderLeft": 1,
        "BorderRight": null
      },
      {
        "FontFamily": 0,
        "FontSize": 14.666666984558105,
        "BorderBottom": null,
        "BorderTop": null,
        "BorderLeft": null,
        "BorderRight": 2
      },
      {
        "FontFamily": 0,
        "FontSize": 14.666666984558105,
        "BorderBottom": 1,
        "BorderTop": null,
        "BorderLeft": 2,
        "BorderRight": null
      },
      {
        "FontFamily": 0,
        "FontSize": 14.666666984558105,
        "BorderBottom": 1,
        "BorderTop": null,
        "BorderLeft": null,
        "BorderRight": null
      },
      {
        "FontFamily": 0,
        "FontSize": 14.666666984558105,
        "BorderBottom": 1,
        "BorderTop": null,
        "BorderLeft": 1,
        "BorderRight": null
      },
      {
        "FontFamily": 0,
        "FontSize": 14.666666984558105,
        "BorderBottom": 1,
        "BorderTop": null,
        "BorderLeft": null,
        "BorderRight": 2
      },
      {
        "Background": 10,
        "FontFamily": 0,
        "FontSize": 14.666666984558105,
        "FontWeight": 8,
        "Foreground": 9,
        "HorizontalAlignment": 16,
        "VerticalAlignment": 12,
        "BorderBottom": null,
        "BorderTop": 1,
        "BorderLeft": 2,
        "BorderRight": null
      },
      {
        "FontFamily": 0,
        "FontSize": 14.666666984558105,
        "Formatter": 4,
        "VerticalAlignment": 12,
        "WordWrap": true,
        "Underline": true,
        "BorderTop": 1,
        "BorderLeft": 1
      },
      {
        "BorderTop": 1
      },
      {
        "BorderTop": 1,
        "BorderRight": 2
      },
      {
        "BorderLeft": 2
      },
      {
        "BorderLeft": 1
      },
      {
        "Background": 10,
        "FontFamily": 0,
        "FontSize": 13.333333333333332,
        "FontWeight": 8,
        "Foreground": 9,
        "Formatter": 15,
        "TextIndent": 5,
        "HorizontalAlignment": 14,
        "BorderBottom": null,
        "BorderTop": null,
        "BorderLeft": 2,
        "BorderRight": null
      },
      {
        "Background": 17
      },
      {
        "BorderBottom": 1,
        "BorderLeft": 1
      },
      {
        "BorderBottom": 1,
        "BorderRight": 2
      },
      {
        "BorderBottom": null,
        "BorderTop": 1,
        "BorderLeft": null,
        "BorderRight": null
      },
      {
        "BorderBottom": null,
        "BorderTop": 1,
        "BorderLeft": null
      },
      {
        "FontFamily": 0,
        "FontSize": 14.666666984558105,
        "Underline": true,
        "BorderBottom": 1,
        "BorderTop": 1,
        "BorderLeft": 1
      },
      {
        "Background": 1,
        "FontFamily": 0,
        "FontSize": 14.666666984558105,
        "Foreground": 18,
        "Formatter": 3,
        "TextIndent": 5,
        "HorizontalAlignment": 14
      },
      {
        "BorderBottom": null,
        "BorderTop": null,
        "BorderLeft": 2,
        "BorderRight": null
      },
      {
        "BorderBottom": null,
        "BorderTop": null,
        "BorderLeft": null,
        "BorderRight": null
      },
      {
        "BorderBottom": null,
        "BorderTop": null,
        "BorderLeft": null
      },
      {
        "BorderBottom": 1,
        "BorderTop": 1,
        "BorderLeft": 1
      },
      {
        "Background": 10,
        "BorderBottom": null,
        "BorderTop": null,
        "BorderLeft": null
      },
      {
        "Background": 10,
        "BorderTop": null,
        "BorderLeft": 2,
        "BorderRight": null
      },
      {
        "Background": 10,
        "BorderTop": null,
        "BorderLeft": null,
        "BorderRight": null
      },
      {
        "Background": 10,
        "BorderTop": null,
        "BorderLeft": null
      },
      {
        "Background": 10,
        "BorderLeft": 2
      },
      {
        "Background": 10
      },
      {
        "Background": 10,
        "Foreground": 18,
        "Formatter": 3,
        "BorderBottom": null,
        "BorderLeft": 2,
        "BorderRight": null
      },
      {
        "Background": 10,
        "Foreground": 18,
        "Formatter": 3,
        "BorderLeft": 2
      },
      {
        "Background": 10,
        "Foreground": 18,
        "Formatter": 3,
        "BorderBottom": 2,
        "BorderLeft": 2
      },
      {
        "Background": 10,
        "BorderBottom": 2
      },
      {
        "BorderBottom": 2,
        "BorderTop": 1,
        "BorderLeft": 1
      },
      {
        "BorderBottom": 2,
        "BorderTop": 1
      },
      {
        "BorderBottom": 2,
        "BorderTop": 1,
        "BorderRight": 2
      },
      {
        "Background": 1,
        "Foreground": 18,
        "Formatter": 3
      }
    ],
    "Types": {
      "Strs": [
        "Meiryo UI",
        "#FFFCFCFC",
        "Blue",
        "[AUTO]General",
        "@",
        "Right",
        "Background 2 0",
        "Background 1 -5",
        "Bold",
        "Accent 4 0",
        "Accent 4 80",
        "#FFFF0000",
        "Top",
        "General",
        "Left",
        "yyyy/m/d",
        "Center",
        "#FFFBE3D5",
        "#FF6D6D6D"
      ],
      "Borders": [
        {
          "Color": 6
        },
        {
          "Color": 9
        },
        {
          "Style": 2,
          "Color": 9
        }
      ]
    },
    "CellStyles": {
      "1,2": 0,
      "1,3": 0,
      "1,4": 1,
      "1,5": 2,
      "1,7": 3,
      "1,40": 4,
      "2,2": 5,
      "2,3": 5,
      "2,4": 6,
      "2,5": 6,
      "2,6": 6,
      "2,7": 6,
      "2,8": 6,
      "2,9": 6,
      "2,10": 6,
      "2,11": 6,
      "2,12": 6,
      "2,13": 6,
      "2,14": 6,
      "2,15": 6,
      "2,16": 6,
      "2,17": 6,
      "2,18": 6,
      "2,19": 6,
      "2,20": 6,
      "2,21": 6,
      "2,22": 6,
      "2,23": 6,
      "2,24": 6,
      "2,25": 6,
      "2,26": 6,
      "2,27": 6,
      "2,28": 6,
      "2,29": 6,
      "2,30": 6,
      "2,31": 6,
      "2,32": 6,
      "2,33": 6,
      "2,34": 6,
      "2,35": 6,
      "2,36": 6,
      "2,37": 6,
      "2,38": 6,
      "4,1": 7,
      "4,29": 8,
      "4,30": 9,
      "4,31": 10,
      "4,32": 10,
      "4,33": 10,
      "4,34": 10,
      "4,35": 10,
      "4,36": 10,
      "4,37": 10,
      "4,38": 10,
      "5,1": 7,
      "5,9": 11,
      "5,10": 12,
      "5,29": 8,
      "5,30": 9,
      "5,31": 10,
      "5,32": 10,
      "5,33": 10,
      "5,34": 10,
      "5,35": 10,
      "5,36": 10,
      "5,37": 10,
      "5,38": 10,
      "6,1": 13,
      "6,2": 13,
      "6,3": 13,
      "6,4": 13,
      "6,29": 14,
      "6,30": 15,
      "6,39": 16,
      "6,40": 16,
      "7,1": 13,
      "7,2": 13,
      "7,3": 13,
      "7,4": 13,
      "7,29": 14,
      "7,30": 17,
      "7,31": 18,
      "7,32": 18,
      "7,33": 18,
      "7,34": 18,
      "7,35": 18,
      "7,36": 18,
      "7,37": 18,
      "7,38": 18,
      "7,39": 16,
      "7,40": 16,
      "8,1": 19,
      "8,2": 19,
      "8,3": 19,
      "8,4": 19,
      "8,5": 19,
      "8,6": 19,
      "8,7": 19,
      "8,8": 19,
      "8,9": 19,
      "8,10": 19,
      "8,11": 19,
      "8,12": 19,
      "8,13": 19,
      "8,14": 19,
      "8,15": 19,
      "8,16": 19,
      "8,17": 19,
      "8,18": 19,
      "8,19": 19,
      "8,20": 19,
      "8,21": 19,
      "8,22": 19,
      "8,23": 19,
      "8,24": 19,
      "8,25": 19,
      "8,26": 19,
      "8,27": 19,
      "8,28": 19,
      "8,29": 19,
      "8,30": 20,
      "8,31": 20,
      "8,32": 20,
      "8,33": 20,
      "8,34": 20,
      "8,35": 20,
      "8,36": 20,
      "8,37": 20,
      "8,38": 20,
      "8,39": 20,
      "8,40": 20,
      "9,1": 21,
      "9,2": 22,
      "9,3": 23,
      "9,4": 23,
      "9,5": 23,
      "9,6": 24,
      "9,7": 23,
      "9,8": 23,
      "9,9": 23,
      "9,10": 23,
      "9,11": 23,
      "9,12": 23,
      "9,13": 23,
      "9,14": 23,
      "9,15": 23,
      "9,16": 23,
      "9,17": 23,
      "9,18": 23,
      "9,19": 23,
      "9,20": 23,
      "9,21": 23,
      "9,22": 23,
      "9,23": 23,
      "9,24": 23,
      "9,25": 25,
      "9,26": 23,
      "9,27": 23,
      "9,28": 23,
      "9,29": 26,
      "9,30": 27,
      "9,31": 23,
      "9,32": 23,
      "9,33": 23,
      "9,34": 23,
      "9,35": 23,
      "9,36": 23,
      "9,37": 23,
      "9,38": 28,
      "9,39": 29,
      "9,40": 29,
      "10,1": 30,
      "10,2": 31,
      "10,3": 18,
      "10,4": 18,
      "10,5": 18,
      "10,6": 32,
      "10,7": 18,
      "10,8": 18,
      "10,9": 18,
      "10,10": 18,
      "10,11": 18,
      "10,12": 18,
      "10,13": 18,
      "10,14": 18,
      "10,15": 18,
      "10,16": 18,
      "10,17": 18,
      "10,18": 18,
      "10,19": 18,
      "10,20": 18,
      "10,21": 18,
      "10,22": 18,
      "10,23": 18,
      "10,24": 18,
      "10,25": 18,
      "10,26": 18,
      "10,27": 18,
      "10,28": 18,
      "10,29": 18,
      "10,30": 18,
      "10,31": 18,
      "10,32": 18,
      "10,33": 18,
      "10,34": 18,
      "10,35": 18,
      "10,36": 18,
      "10,37": 18,
      "10,38": 33,
      "10,39": 16,
      "10,40": 16,
      "11,1": 34,
      "11,6": 35,
      "11,38": 36,
      "11,39": 16,
      "11,40": 16,
      "12,1": 37,
      "12,2": 38,
      "12,3": 38,
      "12,4": 38,
      "12,5": 38,
      "12,6": 39,
      "12,7": 38,
      "12,8": 38,
      "12,9": 38,
      "12,10": 38,
      "12,11": 38,
      "12,12": 38,
      "12,13": 38,
      "12,14": 38,
      "12,15": 38,
      "12,16": 38,
      "12,17": 38,
      "12,18": 38,
      "12,19": 38,
      "12,20": 38,
      "12,21": 38,
      "12,22": 38,
      "12,23": 38,
      "12,24": 38,
      "12,25": 38,
      "12,26": 38,
      "12,27": 38,
      "12,28": 38,
      "12,29": 38,
      "12,30": 38,
      "12,31": 38,
      "12,32": 38,
      "12,33": 38,
      "12,34": 38,
      "12,35": 38,
      "12,36": 38,
      "12,37": 38,
      "12,38": 40,
      "12,39": 16,
      "12,40": 16,
      "13,1": 41,
      "13,2": 0,
      "13,3": 0,
      "13,4": 0,
      "13,5": 0,
      "13,6": 42,
      "13,7": 0,
      "13,8": 0,
      "13,9": 0,
      "13,10": 0,
      "13,11": 0,
      "13,12": 0,
      "13,13": 0,
      "13,14": 0,
      "13,15": 0,
      "13,16": 0,
      "13,17": 0,
      "13,18": 0,
      "13,19": 0,
      "13,20": 0,
      "13,21": 0,
      "13,22": 0,
      "13,23": 0,
      "13,24": 0,
      "13,25": 0,
      "13,26": 0,
      "13,27": 0,
      "13,28": 0,
      "13,29": 0,
      "13,30": 0,
      "13,31": 0,
      "13,32": 0,
      "13,33": 0,
      "13,34": 0,
      "13,35": 0,
      "13,36": 0,
      "13,37": 0,
      "13,38": 43,
      "13,39": 16,
      "13,40": 16,
      "14,1": 41,
      "14,2": 0,
      "14,3": 0,
      "14,4": 0,
      "14,5": 0,
      "14,6": 42,
      "14,7": 0,
      "14,8": 0,
      "14,9": 0,
      "14,10": 0,
      "14,11": 0,
      "14,12": 0,
      "14,13": 0,
      "14,14": 0,
      "14,15": 0,
      "14,16": 0,
      "14,17": 0,
      "14,18": 0,
      "14,19": 0,
      "14,20": 0,
      "14,21": 0,
      "14,22": 0,
      "14,23": 0,
      "14,24": 0,
      "14,25": 0,
      "14,26": 0,
      "14,27": 0,
      "14,28": 0,
      "14,29": 0,
      "14,30": 0,
      "14,31": 0,
      "14,32": 0,
      "14,33": 0,
      "14,34": 0,
      "14,35": 0,
      "14,36": 0,
      "14,37": 0,
      "14,38": 43,
      "14,39": 16,
      "14,40": 16,
      "15,1": 44,
      "15,2": 45,
      "15,3": 45,
      "15,4": 45,
      "15,5": 45,
      "15,6": 46,
      "15,7": 45,
      "15,8": 45,
      "15,9": 45,
      "15,10": 45,
      "15,11": 45,
      "15,12": 45,
      "15,13": 45,
      "15,14": 45,
      "15,15": 45,
      "15,16": 45,
      "15,17": 45,
      "15,18": 45,
      "15,19": 45,
      "15,20": 45,
      "15,21": 45,
      "15,22": 45,
      "15,23": 45,
      "15,24": 45,
      "15,25": 45,
      "15,26": 45,
      "15,27": 45,
      "15,28": 45,
      "15,29": 45,
      "15,30": 45,
      "15,31": 45,
      "15,32": 45,
      "15,33": 45,
      "15,34": 45,
      "15,35": 45,
      "15,36": 45,
      "15,37": 45,
      "15,38": 47,
      "15,39": 16,
      "15,40": 16,
      "16,1": 48,
      "16,2": 38,
      "16,3": 38,
      "16,4": 38,
      "16,5": 38,
      "16,6": 49,
      "16,7": 50,
      "16,8": 50,
      "16,9": 50,
      "16,10": 50,
      "16,11": 50,
      "16,12": 50,
      "16,13": 50,
      "16,14": 50,
      "16,15": 50,
      "16,16": 50,
      "16,17": 50,
      "16,18": 50,
      "16,19": 50,
      "16,20": 50,
      "16,21": 50,
      "16,22": 50,
      "16,23": 50,
      "16,24": 50,
      "16,25": 50,
      "16,26": 50,
      "16,27": 50,
      "16,28": 50,
      "16,29": 50,
      "16,30": 50,
      "16,31": 50,
      "16,32": 50,
      "16,33": 50,
      "16,34": 50,
      "16,35": 50,
      "16,36": 50,
      "16,37": 50,
      "16,38": 51,
      "16,39": 16,
      "16,40": 16,
      "17,1": 52,
      "17,6": 53,
      "17,38": 36,
      "17,39": 16,
      "17,40": 16,
      "18,1": 41,
      "18,2": 0,
      "18,3": 0,
      "18,4": 0,
      "18,5": 0,
      "18,6": 53,
      "18,38": 36,
      "18,39": 16,
      "18,40": 16,
      "19,1": 54,
      "19,2": 0,
      "19,3": 0,
      "19,4": 0,
      "19,5": 55,
      "19,6": 56,
      "19,7": 10,
      "19,8": 10,
      "19,9": 10,
      "19,10": 10,
      "19,11": 10,
      "19,12": 10,
      "19,13": 10,
      "19,14": 10,
      "19,15": 10,
      "19,16": 10,
      "19,17": 10,
      "19,18": 10,
      "19,19": 10,
      "19,20": 10,
      "19,21": 10,
      "19,22": 10,
      "19,23": 10,
      "19,24": 10,
      "19,25": 10,
      "19,26": 10,
      "19,27": 10,
      "19,28": 10,
      "19,29": 10,
      "19,30": 10,
      "19,31": 10,
      "19,32": 10,
      "19,33": 10,
      "19,34": 10,
      "19,35": 10,
      "19,36": 10,
      "19,37": 10,
      "19,38": 57,
      "19,39": 16,
      "19,40": 16,
      "20,1": 48,
      "20,2": 58,
      "20,3": 58,
      "20,4": 58,
      "20,5": 59,
      "20,6": 60,
      "20,7": 18,
      "20,8": 18,
      "20,9": 18,
      "20,10": 18,
      "20,11": 18,
      "20,12": 18,
      "20,13": 18,
      "20,14": 18,
      "20,15": 18,
      "20,16": 18,
      "20,17": 18,
      "20,18": 18,
      "20,19": 18,
      "20,20": 18,
      "20,21": 18,
      "20,22": 18,
      "20,23": 18,
      "20,24": 18,
      "20,25": 18,
      "20,26": 18,
      "20,27": 18,
      "20,28": 18,
      "20,29": 18,
      "20,30": 18,
      "20,31": 18,
      "20,32": 18,
      "20,33": 18,
      "20,34": 18,
      "20,35": 18,
      "20,36": 18,
      "20,37": 18,
      "20,38": 33,
      "20,39": 61,
      "20,40": 61,
      "21,1": 62,
      "21,2": 63,
      "21,3": 63,
      "21,4": 63,
      "21,5": 64,
      "21,6": 65,
      "21,7": 18,
      "21,8": 18,
      "21,9": 18,
      "21,10": 18,
      "21,11": 18,
      "21,12": 18,
      "21,13": 18,
      "21,14": 18,
      "21,15": 18,
      "21,16": 18,
      "21,17": 18,
      "21,18": 18,
      "21,19": 18,
      "21,20": 18,
      "21,21": 18,
      "21,22": 18,
      "21,23": 18,
      "21,24": 18,
      "21,25": 18,
      "21,26": 18,
      "21,27": 18,
      "21,28": 18,
      "21,29": 18,
      "21,30": 18,
      "21,31": 18,
      "21,32": 18,
      "21,33": 18,
      "21,34": 18,
      "21,35": 18,
      "21,36": 18,
      "21,37": 18,
      "21,38": 33,
      "22,1": 54,
      "22,2": 0,
      "22,3": 0,
      "22,4": 0,
      "22,5": 66,
      "22,6": 65,
      "22,7": 18,
      "22,8": 18,
      "22,9": 18,
      "22,10": 18,
      "22,11": 18,
      "22,12": 18,
      "22,13": 18,
      "22,14": 18,
      "22,15": 18,
      "22,16": 18,
      "22,17": 18,
      "22,18": 18,
      "22,19": 18,
      "22,20": 18,
      "22,21": 18,
      "22,22": 18,
      "22,23": 18,
      "22,24": 18,
      "22,25": 18,
      "22,26": 18,
      "22,27": 18,
      "22,28": 18,
      "22,29": 18,
      "22,30": 18,
      "22,31": 18,
      "22,32": 18,
      "22,33": 18,
      "22,34": 18,
      "22,35": 18,
      "22,36": 18,
      "22,37": 18,
      "22,38": 33,
      "23,1": 67,
      "23,2": 68,
      "23,3": 68,
      "23,4": 68,
      "23,5": 69,
      "23,6": 65,
      "23,7": 18,
      "23,8": 18,
      "23,9": 18,
      "23,10": 18,
      "23,11": 18,
      "23,12": 18,
      "23,13": 18,
      "23,14": 18,
      "23,15": 18,
      "23,16": 18,
      "23,17": 18,
      "23,18": 18,
      "23,19": 18,
      "23,20": 18,
      "23,21": 18,
      "23,22": 18,
      "23,23": 18,
      "23,24": 18,
      "23,25": 18,
      "23,26": 18,
      "23,27": 18,
      "23,28": 18,
      "23,29": 18,
      "23,30": 18,
      "23,31": 18,
      "23,32": 18,
      "23,33": 18,
      "23,34": 18,
      "23,35": 18,
      "23,36": 18,
      "23,37": 18,
      "23,38": 33,
      "24,1": 70,
      "24,2": 71,
      "24,3": 71,
      "24,4": 71,
      "24,5": 71,
      "24,6": 65,
      "24,7": 18,
      "24,8": 18,
      "24,9": 18,
      "24,10": 18,
      "24,11": 18,
      "24,12": 18,
      "24,13": 18,
      "24,14": 18,
      "24,15": 18,
      "24,16": 18,
      "24,17": 18,
      "24,18": 18,
      "24,19": 18,
      "24,20": 18,
      "24,21": 18,
      "24,22": 18,
      "24,23": 18,
      "24,24": 18,
      "24,25": 18,
      "24,26": 18,
      "24,27": 18,
      "24,28": 18,
      "24,29": 18,
      "24,30": 18,
      "24,31": 18,
      "24,32": 18,
      "24,33": 18,
      "24,34": 18,
      "24,35": 18,
      "24,36": 18,
      "24,37": 18,
      "24,38": 33,
      "25,1": 72,
      "25,2": 71,
      "25,3": 71,
      "25,4": 71,
      "25,5": 71,
      "25,6": 65,
      "25,7": 18,
      "25,8": 18,
      "25,9": 18,
      "25,10": 18,
      "25,11": 18,
      "25,12": 18,
      "25,13": 18,
      "25,14": 18,
      "25,15": 18,
      "25,16": 18,
      "25,17": 18,
      "25,18": 18,
      "25,19": 18,
      "25,20": 18,
      "25,21": 18,
      "25,22": 18,
      "25,23": 18,
      "25,24": 18,
      "25,25": 18,
      "25,26": 18,
      "25,27": 18,
      "25,28": 18,
      "25,29": 18,
      "25,30": 18,
      "25,31": 18,
      "25,32": 18,
      "25,33": 18,
      "25,34": 18,
      "25,35": 18,
      "25,36": 18,
      "25,37": 18,
      "25,38": 33,
      "26,1": 73,
      "26,2": 71,
      "26,3": 71,
      "26,4": 71,
      "26,5": 71,
      "26,6": 65,
      "26,7": 18,
      "26,8": 18,
      "26,9": 18,
      "26,10": 18,
      "26,11": 18,
      "26,12": 18,
      "26,13": 18,
      "26,14": 18,
      "26,15": 18,
      "26,16": 18,
      "26,17": 18,
      "26,18": 18,
      "26,19": 18,
      "26,20": 18,
      "26,21": 18,
      "26,22": 18,
      "26,23": 18,
      "26,24": 18,
      "26,25": 18,
      "26,26": 18,
      "26,27": 18,
      "26,28": 18,
      "26,29": 18,
      "26,30": 18,
      "26,31": 18,
      "26,32": 18,
      "26,33": 18,
      "26,34": 18,
      "26,35": 18,
      "26,36": 18,
      "26,37": 18,
      "26,38": 33,
      "27,1": 73,
      "27,2": 71,
      "27,3": 71,
      "27,4": 71,
      "27,5": 71,
      "27,6": 65,
      "27,7": 18,
      "27,8": 18,
      "27,9": 18,
      "27,10": 18,
      "27,11": 18,
      "27,12": 18,
      "27,13": 18,
      "27,14": 18,
      "27,15": 18,
      "27,16": 18,
      "27,17": 18,
      "27,18": 18,
      "27,19": 18,
      "27,20": 18,
      "27,21": 18,
      "27,22": 18,
      "27,23": 18,
      "27,24": 18,
      "27,25": 18,
      "27,26": 18,
      "27,27": 18,
      "27,28": 18,
      "27,29": 18,
      "27,30": 18,
      "27,31": 18,
      "27,32": 18,
      "27,33": 18,
      "27,34": 18,
      "27,35": 18,
      "27,36": 18,
      "27,37": 18,
      "27,38": 33,
      "28,1": 73,
      "28,2": 71,
      "28,3": 71,
      "28,4": 71,
      "28,5": 71,
      "28,6": 65,
      "28,7": 18,
      "28,8": 18,
      "28,9": 18,
      "28,10": 18,
      "28,11": 18,
      "28,12": 18,
      "28,13": 18,
      "28,14": 18,
      "28,15": 18,
      "28,16": 18,
      "28,17": 18,
      "28,18": 18,
      "28,19": 18,
      "28,20": 18,
      "28,21": 18,
      "28,22": 18,
      "28,23": 18,
      "28,24": 18,
      "28,25": 18,
      "28,26": 18,
      "28,27": 18,
      "28,28": 18,
      "28,29": 18,
      "28,30": 18,
      "28,31": 18,
      "28,32": 18,
      "28,33": 18,
      "28,34": 18,
      "28,35": 18,
      "28,36": 18,
      "28,37": 18,
      "28,38": 33,
      "29,1": 73,
      "29,2": 71,
      "29,3": 71,
      "29,4": 71,
      "29,5": 71,
      "29,6": 65,
      "29,7": 18,
      "29,8": 18,
      "29,9": 18,
      "29,10": 18,
      "29,11": 18,
      "29,12": 18,
      "29,13": 18,
      "29,14": 18,
      "29,15": 18,
      "29,16": 18,
      "29,17": 18,
      "29,18": 18,
      "29,19": 18,
      "29,20": 18,
      "29,21": 18,
      "29,22": 18,
      "29,23": 18,
      "29,24": 18,
      "29,25": 18,
      "29,26": 18,
      "29,27": 18,
      "29,28": 18,
      "29,29": 18,
      "29,30": 18,
      "29,31": 18,
      "29,32": 18,
      "29,33": 18,
      "29,34": 18,
      "29,35": 18,
      "29,36": 18,
      "29,37": 18,
      "29,38": 33,
      "30,1": 73,
      "30,2": 71,
      "30,3": 71,
      "30,4": 71,
      "30,5": 71,
      "30,6": 65,
      "30,7": 18,
      "30,8": 18,
      "30,9": 18,
      "30,10": 18,
      "30,11": 18,
      "30,12": 18,
      "30,13": 18,
      "30,14": 18,
      "30,15": 18,
      "30,16": 18,
      "30,17": 18,
      "30,18": 18,
      "30,19": 18,
      "30,20": 18,
      "30,21": 18,
      "30,22": 18,
      "30,23": 18,
      "30,24": 18,
      "30,25": 18,
      "30,26": 18,
      "30,27": 18,
      "30,28": 18,
      "30,29": 18,
      "30,30": 18,
      "30,31": 18,
      "30,32": 18,
      "30,33": 18,
      "30,34": 18,
      "30,35": 18,
      "30,36": 18,
      "30,37": 18,
      "30,38": 33,
      "31,1": 73,
      "31,2": 71,
      "31,3": 71,
      "31,4": 71,
      "31,5": 71,
      "31,6": 65,
      "31,7": 18,
      "31,8": 18,
      "31,9": 18,
      "31,10": 18,
      "31,11": 18,
      "31,12": 18,
      "31,13": 18,
      "31,14": 18,
      "31,15": 18,
      "31,16": 18,
      "31,17": 18,
      "31,18": 18,
      "31,19": 18,
      "31,20": 18,
      "31,21": 18,
      "31,22": 18,
      "31,23": 18,
      "31,24": 18,
      "31,25": 18,
      "31,26": 18,
      "31,27": 18,
      "31,28": 18,
      "31,29": 18,
      "31,30": 18,
      "31,31": 18,
      "31,32": 18,
      "31,33": 18,
      "31,34": 18,
      "31,35": 18,
      "31,36": 18,
      "31,37": 18,
      "31,38": 33,
      "32,1": 73,
      "32,2": 71,
      "32,3": 71,
      "32,4": 71,
      "32,5": 71,
      "32,6": 65,
      "32,7": 18,
      "32,8": 18,
      "32,9": 18,
      "32,10": 18,
      "32,11": 18,
      "32,12": 18,
      "32,13": 18,
      "32,14": 18,
      "32,15": 18,
      "32,16": 18,
      "32,17": 18,
      "32,18": 18,
      "32,19": 18,
      "32,20": 18,
      "32,21": 18,
      "32,22": 18,
      "32,23": 18,
      "32,24": 18,
      "32,25": 18,
      "32,26": 18,
      "32,27": 18,
      "32,28": 18,
      "32,29": 18,
      "32,30": 18,
      "32,31": 18,
      "32,32": 18,
      "32,33": 18,
      "32,34": 18,
      "32,35": 18,
      "32,36": 18,
      "32,37": 18,
      "32,38": 33,
      "33,1": 73,
      "33,2": 71,
      "33,3": 71,
      "33,4": 71,
      "33,5": 71,
      "33,6": 65,
      "33,7": 18,
      "33,8": 18,
      "33,9": 18,
      "33,10": 18,
      "33,11": 18,
      "33,12": 18,
      "33,13": 18,
      "33,14": 18,
      "33,15": 18,
      "33,16": 18,
      "33,17": 18,
      "33,18": 18,
      "33,19": 18,
      "33,20": 18,
      "33,21": 18,
      "33,22": 18,
      "33,23": 18,
      "33,24": 18,
      "33,25": 18,
      "33,26": 18,
      "33,27": 18,
      "33,28": 18,
      "33,29": 18,
      "33,30": 18,
      "33,31": 18,
      "33,32": 18,
      "33,33": 18,
      "33,34": 18,
      "33,35": 18,
      "33,36": 18,
      "33,37": 18,
      "33,38": 33,
      "34,1": 73,
      "34,2": 71,
      "34,3": 71,
      "34,4": 71,
      "34,5": 71,
      "34,6": 65,
      "34,7": 18,
      "34,8": 18,
      "34,9": 18,
      "34,10": 18,
      "34,11": 18,
      "34,12": 18,
      "34,13": 18,
      "34,14": 18,
      "34,15": 18,
      "34,16": 18,
      "34,17": 18,
      "34,18": 18,
      "34,19": 18,
      "34,20": 18,
      "34,21": 18,
      "34,22": 18,
      "34,23": 18,
      "34,24": 18,
      "34,25": 18,
      "34,26": 18,
      "34,27": 18,
      "34,28": 18,
      "34,29": 18,
      "34,30": 18,
      "34,31": 18,
      "34,32": 18,
      "34,33": 18,
      "34,34": 18,
      "34,35": 18,
      "34,36": 18,
      "34,37": 18,
      "34,38": 33,
      "35,1": 73,
      "35,2": 71,
      "35,3": 71,
      "35,4": 71,
      "35,5": 71,
      "35,6": 65,
      "35,7": 18,
      "35,8": 18,
      "35,9": 18,
      "35,10": 18,
      "35,11": 18,
      "35,12": 18,
      "35,13": 18,
      "35,14": 18,
      "35,15": 18,
      "35,16": 18,
      "35,17": 18,
      "35,18": 18,
      "35,19": 18,
      "35,20": 18,
      "35,21": 18,
      "35,22": 18,
      "35,23": 18,
      "35,24": 18,
      "35,25": 18,
      "35,26": 18,
      "35,27": 18,
      "35,28": 18,
      "35,29": 18,
      "35,30": 18,
      "35,31": 18,
      "35,32": 18,
      "35,33": 18,
      "35,34": 18,
      "35,35": 18,
      "35,36": 18,
      "35,37": 18,
      "35,38": 33,
      "36,1": 73,
      "36,2": 71,
      "36,3": 71,
      "36,4": 71,
      "36,5": 71,
      "36,6": 65,
      "36,7": 18,
      "36,8": 18,
      "36,9": 18,
      "36,10": 18,
      "36,11": 18,
      "36,12": 18,
      "36,13": 18,
      "36,14": 18,
      "36,15": 18,
      "36,16": 18,
      "36,17": 18,
      "36,18": 18,
      "36,19": 18,
      "36,20": 18,
      "36,21": 18,
      "36,22": 18,
      "36,23": 18,
      "36,24": 18,
      "36,25": 18,
      "36,26": 18,
      "36,27": 18,
      "36,28": 18,
      "36,29": 18,
      "36,30": 18,
      "36,31": 18,
      "36,32": 18,
      "36,33": 18,
      "36,34": 18,
      "36,35": 18,
      "36,36": 18,
      "36,37": 18,
      "36,38": 33,
      "37,1": 73,
      "37,2": 71,
      "37,3": 71,
      "37,4": 71,
      "37,5": 71,
      "37,6": 65,
      "37,7": 18,
      "37,8": 18,
      "37,9": 18,
      "37,10": 18,
      "37,11": 18,
      "37,12": 18,
      "37,13": 18,
      "37,14": 18,
      "37,15": 18,
      "37,16": 18,
      "37,17": 18,
      "37,18": 18,
      "37,19": 18,
      "37,20": 18,
      "37,21": 18,
      "37,22": 18,
      "37,23": 18,
      "37,24": 18,
      "37,25": 18,
      "37,26": 18,
      "37,27": 18,
      "37,28": 18,
      "37,29": 18,
      "37,30": 18,
      "37,31": 18,
      "37,32": 18,
      "37,33": 18,
      "37,34": 18,
      "37,35": 18,
      "37,36": 18,
      "37,37": 18,
      "37,38": 33,
      "38,1": 73,
      "38,2": 71,
      "38,3": 71,
      "38,4": 71,
      "38,5": 71,
      "38,6": 65,
      "38,7": 18,
      "38,8": 18,
      "38,9": 18,
      "38,10": 18,
      "38,11": 18,
      "38,12": 18,
      "38,13": 18,
      "38,14": 18,
      "38,15": 18,
      "38,16": 18,
      "38,17": 18,
      "38,18": 18,
      "38,19": 18,
      "38,20": 18,
      "38,21": 18,
      "38,22": 18,
      "38,23": 18,
      "38,24": 18,
      "38,25": 18,
      "38,26": 18,
      "38,27": 18,
      "38,28": 18,
      "38,29": 18,
      "38,30": 18,
      "38,31": 18,
      "38,32": 18,
      "38,33": 18,
      "38,34": 18,
      "38,35": 18,
      "38,36": 18,
      "38,37": 18,
      "38,38": 33,
      "39,1": 73,
      "39,2": 71,
      "39,3": 71,
      "39,4": 71,
      "39,5": 71,
      "39,6": 65,
      "39,7": 18,
      "39,8": 18,
      "39,9": 18,
      "39,10": 18,
      "39,11": 18,
      "39,12": 18,
      "39,13": 18,
      "39,14": 18,
      "39,15": 18,
      "39,16": 18,
      "39,17": 18,
      "39,18": 18,
      "39,19": 18,
      "39,20": 18,
      "39,21": 18,
      "39,22": 18,
      "39,23": 18,
      "39,24": 18,
      "39,25": 18,
      "39,26": 18,
      "39,27": 18,
      "39,28": 18,
      "39,29": 18,
      "39,30": 18,
      "39,31": 18,
      "39,32": 18,
      "39,33": 18,
      "39,34": 18,
      "39,35": 18,
      "39,36": 18,
      "39,37": 18,
      "39,38": 33,
      "40,1": 74,
      "40,2": 75,
      "40,3": 75,
      "40,4": 75,
      "40,5": 75,
      "40,6": 76,
      "40,7": 77,
      "40,8": 77,
      "40,9": 77,
      "40,10": 77,
      "40,11": 77,
      "40,12": 77,
      "40,13": 77,
      "40,14": 77,
      "40,15": 77,
      "40,16": 77,
      "40,17": 77,
      "40,18": 77,
      "40,19": 77,
      "40,20": 77,
      "40,21": 77,
      "40,22": 77,
      "40,23": 77,
      "40,24": 77,
      "40,25": 77,
      "40,26": 77,
      "40,27": 77,
      "40,28": 77,
      "40,29": 77,
      "40,30": 77,
      "40,31": 77,
      "40,32": 77,
      "40,33": 77,
      "40,34": 77,
      "40,35": 77,
      "40,36": 77,
      "40,37": 77,
      "40,38": 78,
      "41,1": 79
    },
    "SheetStyle": {
      "FontFamily": 0,
      "FontSize": 14.666666984558105,
      "BorderBottom": null,
      "BorderTop": null,
      "BorderLeft": null,
      "BorderRight": null
    }
  },
  "Spans": [
    "20,1,2,5",
    "22,1,1,4",
    "20,6,21,33",
    "10,6,1,33",
    "7,30,1,9",
    "6,30,1,9",
    "5,30,1,9",
    "4,30,1,9",
    "9,2,1,4",
    "10,2,1,4",
    "5,1,1,4",
    "16,1,3,5",
    "19,1,1,4",
    "6,1,2,4",
    "16,6,4,33",
    "9,6,1,19",
    "9,25,1,5",
    "9,30,1,9",
    "12,1,4,5",
    "12,6,4,33",
    "11,1,1,5",
    "11,6,1,33",
    "1,2,2,2",
    "4,1,1,4"
  ],
  "PageInfo": {
    "$type": "Forguncy.Model.Pages.NormalPage, ServerDesignerCommon",
    "Title": "記録文書の編集",
    "PageLoadedCommandList": [
      {
        "$type": "Forguncy.Model.QueryCommand, ServerDesignerCommon",
        "TargetTableName": "trn_insptool_tools",
        "SqlCondition": {
          "$type": "ForguncyDataAccess.GeneralCESqlCondition, ForguncyDataAccess",
          "ColumnBindingInfo": {
            "TableName": "trn_insptool_tools",
            "ColumnName": "ctrl_no"
          },
          "Value": {
            "$type": "Forguncy.Model.FormulaReferObject, ServerDesignerCommon",
            "SerializeProperty": "=記録文書の編集!AO2"
          }
        },
        "Params": [
          "=AO2"
        ],
        "ID": "ab529a7d86a64977bc3b20519dff2ce0"
      }
    ],
    "AuthorizeInfo": {
      "VisitMode": 6,
      "AllowVisitedRoles": [
        "IT戦略室",
        "製造課",
        "九州製造課",
        "業務管理課",
        "製造部",
        "品質保証課",
        "基礎開発課",
        "電気設計課",
        "サービス部"
      ]
    },
    "RowBreakLines": [],
    "RepeatRangeSettings": [],
    "RelatedDataTableName": "trn_insptool_certifications",
    "PageResponsiveMode": 1
  },
  "PrintInfo": {
    "Margin": {},
    "PaperSize": {}
  }
}//X/qtk1mrKL4L2k+E1nIs1zb6ArlGufNOerN4SZZpxzvxiXViGk3M5m9WVXgxwiYOxL9bnruYHIv+QRb//KBVe84s/OqqHPrUS5jgsbdGGs0mZYUhO+Q49YSl3K6GaOzPsMbgzr8bFKENLa+Bsqs5FI6Grk480Ewx/HfBMsLwUbvxBxgN49PY1gZVh4rE6aXXtPv0cNbBqQlu8e0BimaQRAjlj7vV0uj2drjgMNm8AS8ZAVBMXCFiYrUg2K7BfUKe8tZUxwGaXlJPnrGQVNM+D0gaOpRlwJnLoO7J9E3UQ+1Kj+/aa9Q35hZbMK0e75VCjpJWl7WlTTzVOjYSlNt39ngauM3+vh8Ufmj6MZs0ZH/P+N6mn+0mS9A4pXejtKPawLuC+/EIt49k9KqpNGGWDPooFBS69kvCT4pqIXs0TAX+5AamV/Pf2++WGQexXC1N9rZD7VY360s3fRU+IoHPS5S57dcAmobOknkdwD3CDzamMhbfcmdT4v0tyM7UWiJy/llolmq75/nJZ+9fOyF6EmtF4iZw0LOEF4Bk6CugqSHzObvgyU71kaapZfm+aHYB1NhPnAjXMQ4JD8NhYW18ZlcKkaTQJPRmWxZtXzBSoV+JOJ6fPb9I5e0u+KXYAJv/W4cxb2zXLyrCMbE6du4A+wI6m+hIOENmLYE/mCbkOH1G/BWQv1H/z6Z9xctzyqwFXkO9Mklt+GIqA0MBzoJaQohEz3U2mdzlbou0qToctMLytqbDmUbL+Bi08tPnGxq1N/9xjonXZAdhKj0wVCKBHZM4irt+Cv+bLmIMCSXLDU84prevzbL/1Qb4sfdZ3YKxiJEqAm82zLZldxH92qq/TLW9rGs/0ekKPC0gqdMeDcuwRBXR6+HY+00PzrGBdtrKWKAA/mH5CcJD7allT2liVA==|920